odoo10_addon_web_advanced_search_x2x-10.0.2.0.3-py2.7-nspkg.pth
odoo/addons/web_advanced_search_x2x/README.rst
odoo/addons/web_advanced_search_x2x/__init__.py
odoo/addons/web_advanced_search_x2x/__manifest__.py
odoo/addons/web_advanced_search_x2x/i18n/es.po
odoo/addons/web_advanced_search_x2x/i18n/fr.po
odoo/addons/web_advanced_search_x2x/i18n/hr.po
odoo/addons/web_advanced_search_x2x/i18n/nl.po
odoo/addons/web_advanced_search_x2x/i18n/nl_NL.po
odoo/addons/web_advanced_search_x2x/i18n/pt_BR.po
odoo/addons/web_advanced_search_x2x/i18n/web_advanced_search_x2x.pot
odoo/addons/web_advanced_search_x2x/static/description/icon.png
odoo/addons/web_advanced_search_x2x/static/src/css/web_advanced_search_x2x.less
odoo/addons/web_advanced_search_x2x/static/src/js/web_advanced_search_x2x.js
odoo/addons/web_advanced_search_x2x/static/src/xml/web_advanced_search_x2x.xml
odoo/addons/web_advanced_search_x2x/views/templates.xml
odoo10_addon_web_advanced_search_x2x-10.0.2.0.3.dist-info/DESCRIPTION.rst
odoo10_addon_web_advanced_search_x2x-10.0.2.0.3.dist-info/METADATA
odoo10_addon_web_advanced_search_x2x-10.0.2.0.3.dist-info/RECORD
odoo10_addon_web_advanced_search_x2x-10.0.2.0.3.dist-info/WHEEL
odoo10_addon_web_advanced_search_x2x-10.0.2.0.3.dist-info/metadata.json
odoo10_addon_web_advanced_search_x2x-10.0.2.0.3.dist-info/namespace_packages.txt
odoo10_addon_web_advanced_search_x2x-10.0.2.0.3.dist-info/top_level.txt
