Metadata-Version: 2.0
Name: odoo10-addon-web-advanced-search-x2x
Version: 10.0.2.0.3
Summary: Use a search widget in advanced search for x2x fields
Home-page: UNKNOWN
Author: Therp BV, Tecnativa, Odoo Community Association (OCA)
Author-email: support@odoo-community.org
License: AGPL-3
Platform: UNKNOWN
Classifier: Programming Language :: Python
Classifier: Framework :: Odoo
Classifier: License :: OSI Approved :: GNU Affero General Public License v3
Requires-Python: ~=2.7
Requires-Dist: odoo (<10.1dev,>=10.0)
Requires-Dist: odoo10-addon-web-widget-domain-v11
